predict/__init__.py
predict/layers.py
predict/model.py
predict/predict.py
predict/utils.py
predict/测试.py
predict0.1-0.1.0.dist-info/LICENSE.txt
predict0.1-0.1.0.dist-info/METADATA
predict0.1-0.1.0.dist-info/WHEEL
predict0.1-0.1.0.dist-info/top_level.txt
predict0.1-0.1.0.dist-info/RECORD
