Metadata-Version: 2.1
Name: predict0.1
Version: 0.1.0
Summary: Predicting Chemical Molecules
Home-page: https://github.com/
Author: jingyou
Author-email: 1346287203@qq.com
License: MIT
Classifier: License :: OSI Approved :: MIT License
Classifier: Programming Language :: Python
Classifier: Programming Language :: Python :: 3
Classifier: Programming Language :: Python :: 3.6
Classifier: Programming Language :: Python :: Implementation :: CPython
Classifier: Programming Language :: Python :: Implementation :: PyPy
Requires-Python: >=3.6.0
License-File: LICENSE.txt
